LICENSE
MANIFEST.in
README
README.rst
setup.py
tinyrecord/__init__.py
tinyrecord/changeset.py
tinyrecord/operations.py
tinyrecord/transaction.py
tinyrecord.egg-info/PKG-INFO
tinyrecord.egg-info/SOURCES.txt
tinyrecord.egg-info/dependency_links.txt
tinyrecord.egg-info/top_level.txt
tinyrecord.egg-info/zip-safe