Metadata-Version: 2.1
Name: tinyrecord
Version: 0.2.0
Summary: Atomic transactions for TinyDB
Home-page: https://github.com/eugene-eeo/tinyrecord
Author: Eugene Eeo
Author-email: 141bytes@gmail.com
License: MIT
Keywords: tinydb nosql database transaction
Platform: UNKNOWN
Classifier: Development Status :: 5 - Production/Stable
Classifier: Intended Audience :: Developers
Classifier: License :: OSI Approved :: MIT License
Classifier: Programming Language :: Python
Classifier: Programming Language :: Python :: 3.5
Classifier: Programming Language :: Python :: 3.6
Classifier: Programming Language :: Python :: 3.7
Classifier: Programming Language :: Python :: 3.8
Classifier: Programming Language :: Python :: 3 :: Only
Classifier: Topic :: Software Development :: Libraries :: Python Modules
Classifier: Operating System :: Microsoft :: Windows
Classifier: Operating System :: Unix
Classifier: Operating System :: MacOS :: MacOS X
Requires-Python: >=3.5
